[
  {
    "header": "Appetizers",
    "items": [
      {
        "title": "Focaccia",
        "description": "White pizza with olive oil, fresh rosemary and sea salt",
        "price": 8.5
      },{
        "title": "Mozzarella in Carozza",
        "description": "Fried Mozzarella with anchovies. garlic and cream sauce",
        "price": 6.5
      },{
        "title": "Sardine Sandwich",
        "description": "Italian sardines dressed in olive oil",
        "new": true,
        "price": 4
      },{
        "title": "",
        "price": 0
      }
    ]
  },{
    "header": "Salads",
    "items": [
      {
        "title": "Caperse Salad",
        "description": "Ripe tomato with fresh mozzarella and basil",
        "price": 7.5
      },{
        "title": "Arugula Salad",
        "description": "Fresh baby arugula tossed with candied walnuts, roasted beets, dried cranberries & an Asiago Frico in a special house mustard dressing",
        "price": 9.5
      }
    ]
  },{
    "header": "Subs Etc.",
    "items": [
      {
        "title": "The Hero",
        "description": "Breaded or Grilled Chicken topped with Ham, Swiss, Mayo, Mustard, Lettuce",
        "price": 6.79
      },{
        "title": "Chicken Pesto",
        "description": "Basil pesto, provolone, sliced tomatoes, romano cheese and mixed greens",
        "price": 7.95
      },{
        "title": "The Italian Classic",
        "description": "Prosciutto, fresh mozzarella, tomato, arugula, and house oil and vinegar dressing",
        "price": 11.5
      }
    ]
  },{
    "header": "Wood-fried Pizza",
    "items": [
      {
        "title": "Cheese and Tomato",
        "description": "Based on the \"Pines of Rome\" classic",
        "price": 11.75
      },{
        "title": "Basil and Pine Nut Pizza",
        "description": "With sliced tomatoes and mushrooms",
        "price": 12.5
      },{
        "title": "Fresh Herb",
        "description": "A blend of herbs, topped with an olive oil & chèvre cheese",
        "price": 14.75
      },{
        "title": "Garden Veggie",
        "description": "Olives, onions, green peppers, & tomatoes",
        "price": 13.75
      },{
        "title": "Buffalo Chicken",
        "description": "Grilled checken marinated in spicy buffalo sauce",
        "price": 15.75
      },{
        "title": "Pear & Gorgonzola",
        "description": "Caramelized pears, gorgonzola & mozzarella",
        "price": 15.75
      },{
        "title": "Wild Mushtoom",
        "description": "Earthy wild mushrooms with fontinella cheese",
        "price": 14.75
      },{
        "title": "California Club",
        "description": "Applewood smoked bacon & grilled chicken",
        "price": 14.75
      },{
        "title": "Greek Pizza",
        "description": "Mediterranean spiced grilled chicken & mozzarella",
        "price": 14.75
      },{
        "title": "Thai Chicken",
        "description": "Chicken marinated in a spicy peanut-ginger sesame sauce",
        "price": 15.75
      },{
        "title": "Hawaiian BBQ",
        "description": "Fresh pineapple, BBQ chicken, & smoked gouda",
        "price": 16.75
      },{
        "title": "Very Vegan",
        "description": "Crimini mushrooms, roasted garlic, tomatoes, soy cheese",
        "price": 14.75
      }
    ]
  }
]